LICENSE
README.md
setup.py
local_rag_llm/__init__.py
local_rag_llm/db_setup.py
local_rag_llm/local_llm.py
local_rag_llm/model_setup.py
local_rag_llm.egg-info/PKG-INFO
local_rag_llm.egg-info/SOURCES.txt
local_rag_llm.egg-info/dependency_links.txt
local_rag_llm.egg-info/top_level.txt