Metadata-Version: 2.1
Name: local-rag-llm
Version: 0.0.1
Summary: Create and run a local LLM with RAG
Home-page: https://github.com/dhopp1/local_rag_llm
Author: Daniel Hopp
Author-email: daniel.hopp@un.org
Classifier: Programming Language :: Python :: 3
Classifier: License :: OSI Approved :: MIT License
Classifier: Operating System :: OS Independent
Requires-Python: >=3.6
License-File: LICENSE
